idiscore/__init__.py
idiscore/_public_dicom.py
idiscore/annotation.py
idiscore/bouncers.py
idiscore/cli.py
idiscore/core.py
idiscore/dataset.py
idiscore/defaults.py
idiscore/delta.py
idiscore/dicom.py
idiscore/exceptions.py
idiscore/identifiers.py
idiscore/image_processing.py
idiscore/insertions.py
idiscore/logs.py
idiscore/nema_parsing.py
idiscore/operators.py
idiscore/private_processing.py
idiscore/rule_sets.py
idiscore/rules.py
idiscore/settings.py
idiscore/templates.py
idiscore/validation.py
idiscore-1.4.1.dist-info/licenses/LICENSE
idiscore-1.4.1.dist-info/METADATA
idiscore-1.4.1.dist-info/WHEEL
idiscore-1.4.1.dist-info/top_level.txt
idiscore-1.4.1.dist-info/RECORD
