Metadata-Version: 2.4
Name: idiscore
Version: 1.4.1
Summary: Pure-python deidentification of DICOM images using Attribute Confidentiality Options
Author-email: sjoerdk <sjoerd.kerkstra@radboudumc.nl>
Classifier: Programming Language :: Python :: 3.12
Classifier: Programming Language :: Python :: 3.13
Requires-Python: >=3.12
License-File: LICENSE
Requires-Dist: dicomgenerator>=0.9.1
Requires-Dist: jinja2>=3.1.6
Dynamic: license-file
